userinput_vrb/__init__.py
userinput_vrb/__version__.py
userinput_vrb/py.typed
userinput_vrb-1.0.1.dist-info/METADATA
userinput_vrb-1.0.1.dist-info/WHEEL
userinput_vrb-1.0.1.dist-info/licenses/LICENSE
userinput_vrb-1.0.1.dist-info/RECORD
