Metadata-Version: 2.3
Name: userinput_vrb
Version: 1.0.1
Summary: Helper functions for console user input
Project-URL: Homepage, https://github.com/v-r-b/userinput_vrb
Project-URL: Issues, https://github.com/v-r-b/userinput_vrb/issues
Author-email: volker <volker@vrbdev.eu>
Maintainer-email: volker <volker@vrbdev.eu>
License-File: LICENSE
Classifier: Development Status :: 5 - Production/Stable
Classifier: Intended Audience :: Developers
Classifier: License :: OSI Approved :: GNU General Public License v3 (GPLv3)
Classifier: Operating System :: OS Independent
Classifier: Programming Language :: Python :: 3
Classifier: Topic :: Software Development :: Libraries :: Python Modules
Requires-Python: >=3.9
